{
   "agent": "WebSockets",
   "behavior": "OK",
   "behaviorClose": "OK",
   "case": 354,
   "closedByMe": true,
   "createStats": true,
   "createWirelog": true,
   "description": "Send 1000 compressed messages each of payload size 131072, auto-fragment to 256 octets. Use default permessage-deflate offer.",
   "droppedByMe": false,
   "duration": 24131,
   "expectation": "Receive echo'ed messages (with payload as sent). Timeout case after 480 secs.",
   "expected": {},
   "expectedClose": {
      "closeCode": [
         1000
      ],
      "closedByMe": true,
      "requireClean": true
   },
   "failedByMe": false,
   "httpRequest": "GET / HTTP/1.1\r\nUser-Agent: AutobahnTestSuite/0.7.6-0.10.9\r\nHost: localhost:3000\r\nUpgrade: WebSocket\r\nConnection: Upgrade\r\nPragma: no-cache\r\nCache-Control: no-cache\r\nSec-WebSocket-Key: 2Bpg6YnRsotkgv87Zz1C7A==\r\nSec-WebSocket-Extensions: permessage-deflate; client_no_context_takeover; client_max_window_bits\r\nSec-WebSocket-Version: 13\r\n\r\n",
   "httpResponse": "HTTP/1.1 101 Switching Protocols\r\nUpgrade:websocket\r\nConnection:Upgrade\r\nSec-WebSocket-Accept:bkhQD281e3UvCmQc/BIF9MCqHjk=\r\nSec-WebSocket-Extensions:permessage-deflate; client_no_context_takeover\r\n\r\n",
   "id": "12.3.15",
   "isServer": false,
   "localCloseCode": 1000,
   "localCloseReason": null,
   "received": [],
   "remoteCloseCode": 1000,
   "remoteCloseReason": null,
   "reportCompressionRatio": true,
   "reportTime": true,
   "result": "Ok, received all echo'ed messages in time.",
   "resultClose": "Connection was properly closed",
   "rxFrameStats": {
      "2": 1000,
      "8": 1,
      "9": 4
   },
   "rxOctetStats": {
      "4": 1,
      "7": 3,
      "10": 795,
      "199": 1,
      "1296": 3,
      "1470": 36,
      "2756": 3,
      "2930": 13,
      "4216": 1,
      "4390": 5,
      "5850": 4,
      "7136": 1,
      "7310": 6,
      "8596": 4,
      "8770": 4,
      "10056": 2,
      "10230": 4,
      "11516": 1,
      "11690": 7,
      "12976": 1,
      "13150": 5,
      "14610": 2,
      "16070": 7,
      "17356": 3,
      "17530": 5,
      "18816": 98,
      "18990": 5,
      "20276": 4,
      "20450": 6,
      "21736": 4,
      "21910": 4,
      "23196": 5,
      "23370": 2,
      "24656": 4,
      "24820": 1,
      "24830": 7,
      "26116": 7,
      "26123": 1,
      "26290": 1,
      "27576": 4,
      "27740": 1,
      "27750": 5,
      "29036": 6,
      "29200": 3,
      "29210": 3,
      "30496": 6,
      "30660": 1,
      "30670": 2,
      "31956": 7,
      "32130": 1,
      "33416": 1,
      "33580": 3,
      "33590": 4,
      "34876": 3,
      "35040": 3,
      "35050": 3,
      "36336": 5,
      "36500": 4,
      "36510": 2,
      "37796": 5,
      "37960": 3,
      "37970": 1,
      "39256": 1,
      "39420": 4,
      "39430": 4,
      "40716": 8,
      "40880": 1,
      "40890": 3,
      "42176": 2,
      "42340": 5,
      "43636": 4,
      "43800": 3,
      "43810": 1,
      "45096": 6,
      "45260": 2,
      "45270": 2,
      "46556": 5,
      "46720": 48,
      "46730": 50,
      "48016": 5,
      "48180": 2,
      "48190": 1,
      "49476": 7,
      "50936": 2,
      "52396": 5,
      "52560": 1,
      "53856": 7,
      "54020": 1,
      "55316": 4,
      "55480": 2,
      "56776": 4,
      "56940": 3,
      "58236": 6,
      "58400": 1,
      "59696": 4,
      "61156": 5,
      "61320": 1,
      "62616": 13,
      "62780": 3,
      "64076": 36,
      "64240": 3,
      "65536": 1697
   },
   "started": "2017-12-30T23:39:27.962Z",
   "trafficStats": {
      "incomingCompressionRatio": 1.0,
      "incomingOctetsAppLevel": 131072000,
      "incomingOctetsWebSocketLevel": 131072000,
      "incomingOctetsWireLevel": 131082028,
      "incomingWebSocketFrames": 1000,
      "incomingWebSocketMessages": 1000,
      "incomingWebSocketOverhead": 7.6507568359375e-05,
      "outgoingCompressionRatio": 0.38424887084960935,
      "outgoingOctetsAppLevel": 131072000,
      "outgoingOctetsWebSocketLevel": 50364268,
      "outgoingOctetsWireLevel": 51941026,
      "outgoingWebSocketFrames": 197189,
      "outgoingWebSocketMessages": 1000,
      "outgoingWebSocketOverhead": 0.03130707667586869,
      "preopenIncomingOctetsWireLevel": 199,
      "preopenOutgoingOctetsWireLevel": 338
   },
   "txFrameStats": {
      "0": 196189,
      "2": 1000,
      "8": 1,
      "10": 4
   },
   "txOctetStats": {
      "6": 2,
      "7": 3,
      "8": 3,
      "9": 5,
      "10": 8,
      "11": 11,
      "12": 3,
      "13": 2,
      "14": 4,
      "15": 3,
      "16": 1,
      "17": 4,
      "18": 3,
      "19": 1,
      "20": 4,
      "22": 8,
      "23": 1,
      "24": 1,
      "25": 2,
      "26": 1,
      "27": 1,
      "28": 2,
      "29": 4,
      "30": 3,
      "31": 3,
      "32": 3,
      "33": 3,
      "34": 3,
      "35": 3,
      "36": 4,
      "37": 1,
      "38": 5,
      "39": 2,
      "40": 7,
      "41": 3,
      "42": 3,
      "43": 3,
      "44": 4,
      "46": 4,
      "47": 5,
      "48": 2,
      "49": 1,
      "50": 4,
      "51": 3,
      "52": 4,
      "53": 2,
      "54": 2,
      "55": 1,
      "56": 3,
      "57": 3,
      "58": 3,
      "59": 4,
      "60": 1,
      "61": 5,
      "62": 2,
      "63": 1,
      "64": 1,
      "65": 4,
      "66": 3,
      "67": 1,
      "68": 4,
      "69": 1,
      "70": 3,
      "71": 1,
      "72": 1,
      "73": 5,
      "74": 2,
      "75": 3,
      "77": 3,
      "78": 4,
      "80": 5,
      "81": 5,
      "82": 4,
      "83": 6,
      "84": 5,
      "85": 2,
      "86": 4,
      "87": 3,
      "88": 2,
      "89": 3,
      "90": 2,
      "91": 5,
      "92": 3,
      "93": 3,
      "94": 7,
      "95": 10,
      "96": 2,
      "97": 5,
      "98": 6,
      "99": 6,
      "100": 4,
      "101": 4,
      "102": 1,
      "103": 5,
      "104": 4,
      "105": 4,
      "106": 4,
      "107": 2,
      "108": 2,
      "109": 3,
      "110": 1,
      "112": 5,
      "113": 2,
      "114": 1,
      "115": 2,
      "116": 1,
      "117": 1,
      "118": 4,
      "119": 2,
      "120": 2,
      "121": 2,
      "122": 2,
      "123": 6,
      "124": 4,
      "125": 8,
      "126": 3,
      "127": 4,
      "128": 4,
      "129": 4,
      "130": 4,
      "131": 8,
      "134": 3,
      "135": 4,
      "136": 3,
      "137": 6,
      "138": 2,
      "141": 4,
      "142": 2,
      "143": 1,
      "144": 5,
      "145": 7,
      "146": 6,
      "147": 6,
      "148": 4,
      "149": 5,
      "150": 4,
      "151": 9,
      "152": 4,
      "153": 5,
      "154": 4,
      "155": 7,
      "156": 2,
      "157": 8,
      "158": 2,
      "159": 4,
      "160": 5,
      "161": 5,
      "162": 8,
      "163": 8,
      "164": 13,
      "165": 5,
      "166": 8,
      "167": 4,
      "168": 5,
      "169": 10,
      "170": 4,
      "171": 8,
      "172": 5,
      "173": 6,
      "174": 2,
      "175": 9,
      "176": 4,
      "177": 3,
      "178": 4,
      "179": 2,
      "180": 4,
      "181": 1,
      "182": 1,
      "183": 5,
      "184": 4,
      "185": 4,
      "187": 6,
      "188": 6,
      "189": 5,
      "190": 7,
      "191": 5,
      "192": 6,
      "193": 1,
      "194": 4,
      "195": 5,
      "196": 6,
      "197": 7,
      "198": 4,
      "199": 8,
      "200": 3,
      "201": 4,
      "202": 11,
      "203": 4,
      "204": 4,
      "205": 6,
      "206": 7,
      "207": 3,
      "208": 5,
      "209": 2,
      "210": 5,
      "211": 3,
      "212": 4,
      "213": 2,
      "214": 5,
      "215": 7,
      "216": 2,
      "217": 5,
      "218": 2,
      "219": 4,
      "220": 5,
      "221": 5,
      "222": 5,
      "223": 5,
      "224": 3,
      "225": 10,
      "226": 5,
      "227": 4,
      "228": 3,
      "229": 9,
      "230": 6,
      "231": 7,
      "232": 5,
      "233": 4,
      "234": 5,
      "235": 3,
      "236": 1,
      "237": 3,
      "238": 6,
      "239": 4,
      "240": 4,
      "241": 4,
      "242": 5,
      "243": 5,
      "244": 9,
      "245": 4,
      "246": 3,
      "247": 4,
      "248": 5,
      "249": 3,
      "250": 3,
      "251": 5,
      "252": 5,
      "253": 3,
      "254": 4,
      "255": 2,
      "256": 7,
      "258": 6,
      "259": 2,
      "260": 2,
      "261": 8,
      "262": 6,
      "263": 2,
      "264": 196189,
      "338": 1
   },
   "wasClean": true,
   "wasCloseHandshakeTimeout": false,
   "wasNotCleanReason": null,
   "wasOpenHandshakeTimeout": false,
   "wasServerConnectionDropTimeout": false,
   "wirelog": [
      [
         "TO",
         [
            338,
            "474554202f20485454502f312e310d0a557365722d4167656e743a204175746f6261686e5465737453756974652f302e372e362d302e31302e390d0a486f7374 ..."
         ],
         false
      ],
      [
         "RO",
         [
            199,
            "485454502f312e312031303120537769746368696e672050726f746f636f6c730d0a557067726164653a776562736f636b65740d0a436f6e6e656374696f6e3a ..."
         ]
      ],
      [
         "WLM",
         false
      ],
      [
         "TI",
         480
      ],
      [
         "WLM",
         true
      ],
      [
         "TF",
         [
            2,
            "0x03e8"
         ],
         8,
         true,
         0,
         "532c0b9d",
         null,
         null,
         false
      ],
      [
         "TO",
         [
            8,
            "8882532c0b9d50c4"
         ],
         false
      ],
      [
         "RO",
         [
            4,
            "880203e8"
         ]
      ],
      [
         "RF",
         [
            2,
            "0x03e8"
         ],
         8,
         true,
         0,
         false,
         null
      ]
   ]
}